bfast/__init__.py
bfast/base.py
bfast/models.py
bfast/process.py
bfast/utils.py
bfast/cpu/__init__.py
bfast/cpu/base.py
bfast/gpu/__init__.py
bfast/gpu/base.py
bfast/gpu/bfastdistrib.py
bfast/gpu/bfastdistribdetailed.py
bfast/gpu/bfastfinal.py
bfast/gpu/bfastfinaldetailed.py
bfast/gpu/helpers.py
bfast/monitor/__init__.py
bfast/monitor/utils.py
bfast/monitor/c/__init__.py
bfast/monitor/c/base.py
bfast/monitor/opencl/__init__.py
bfast/monitor/opencl/base.py
bfast/monitor/opencl/bfastdistrib.py
bfast/monitor/opencl/bfastdistribdetailed.py
bfast/monitor/opencl/bfastfinal.py
bfast/monitor/opencl/bfastfinaldetailed.py
bfast/monitor/opencl/helpers.py
bfast/monitor/python/__init__.py
bfast/monitor/python/base.py
bfast-0.6.dist-info/LICENSE
bfast-0.6.dist-info/METADATA
bfast-0.6.dist-info/WHEEL
bfast-0.6.dist-info/top_level.txt
bfast-0.6.dist-info/RECORD
