Metadata-Version: 2.1
Name: bfast
Version: 0.6
Summary: A Python library for Breaks For Additive Season and Trend (BFAST) that resorts to parallel computing for accelerating the computations.
Home-page: http://www.bfast.pydata.org
Maintainer: Fabian Gieseke
Maintainer-email: fabian.gieseke@di.ku.dk
License: GNU GENERAL PUBLIC LICENSE
Download-URL: https://github.com/gieseke/bfast
Platform: UNKNOWN
Classifier: Intended Audience :: Science/Research
Classifier: Intended Audience :: Developers
Classifier: License :: OSI Approved
Classifier: Programming Language :: C
Classifier: Programming Language :: Python
Classifier: Topic :: Software Development
Classifier: Topic :: Scientific/Engineering
Classifier: Operating System :: Microsoft :: Windows
Classifier: Operating System :: POSIX
Classifier: Operating System :: Unix
Classifier: Operating System :: MacOS
Classifier: Programming Language :: Python :: 3
Classifier: Programming Language :: Python :: 3.3
Classifier: Programming Language :: Python :: 3.4
Classifier: Programming Language :: Python :: 3.5
Classifier: Programming Language :: Python :: 3.5
Classifier: Programming Language :: Python :: 3.6
Requires-Dist: numpy (>=1.11.0)
Requires-Dist: pandas (>=1.0.0)
Requires-Dist: pyopencl (>=2018.2.5)
Requires-Dist: scikit-learn (>=0.20.3)
Requires-Dist: scipy (>=1.2.1)
Requires-Dist: matplotlib (>=2.2.2)
Requires-Dist: wget (>=3.2)
